opentelemetry/py.typed
opentelemetry/exporter/cloud_monitoring/__init__.py
opentelemetry/exporter/cloud_trace/__init__.py
opentelemetry/exporter/google/version.py
opentelemetry_exporter_google_cloud-0.18b1.dist-info/LICENSE
opentelemetry_exporter_google_cloud-0.18b1.dist-info/METADATA
opentelemetry_exporter_google_cloud-0.18b1.dist-info/WHEEL
opentelemetry_exporter_google_cloud-0.18b1.dist-info/top_level.txt
opentelemetry_exporter_google_cloud-0.18b1.dist-info/RECORD
